hammech/__init__.py
hammech/phase_space.py
hammech-0.1.0.dist-info/licenses/LICENSE
hammech-0.1.0.dist-info/METADATA
hammech-0.1.0.dist-info/WHEEL
hammech-0.1.0.dist-info/top_level.txt
hammech-0.1.0.dist-info/RECORD
